fastinference_onnx/__init__.py
fastinference_onnx/_nbdev.py
fastinference_onnx/tabular.py
fastinference_onnx-0.0.3.dist-info/LICENSE
fastinference_onnx-0.0.3.dist-info/METADATA
fastinference_onnx-0.0.3.dist-info/WHEEL
fastinference_onnx-0.0.3.dist-info/entry_points.txt
fastinference_onnx-0.0.3.dist-info/top_level.txt
fastinference_onnx-0.0.3.dist-info/RECORD
